setup.py
autohome_push.egg-info/PKG-INFO
autohome_push.egg-info/SOURCES.txt
autohome_push.egg-info/dependency_links.txt
autohome_push.egg-info/not-zip-safe
autohome_push.egg-info/requires.txt
autohome_push.egg-info/top_level.txt
push/__init__.py
push/feature.py