Metadata-Version: 1.2
Name: autohome-push
Version: 0.0.1
Summary: a tools that processing feature
Home-page: https://github.com/hisoka176/push
Author: hisoka
Maintainer-email: libin16104@autohome.com.cn
License: UNKNOWN
Keywords: pyspark;machine learning
Platform: UNKNOWN
Requires-Python: ==2.7
